figquilt/__init__.py
figquilt/cli.py
figquilt/compose_pdf.py
figquilt/compose_svg.py
figquilt/errors.py
figquilt/grid.py
figquilt/images.py
figquilt/layout.py
figquilt/parser.py
figquilt/units.py
figquilt-0.1.7.dist-info/WHEEL
figquilt-0.1.7.dist-info/entry_points.txt
figquilt-0.1.7.dist-info/METADATA
figquilt-0.1.7.dist-info/RECORD
