Metadata-Version: 2.3
Name: figquilt
Version: 0.1.7
Summary: figquilt is a small, language-agnostic CLI tool that composes multiple figures (PDF/SVG/PNG) into a single publication-ready figure, based on a simple layout file (YAML/JSON). The key function is creating a PDF by composing multiple PDFs and adding subfigure labels and minimal annotations.
Author: YY Ahn
Author-email: YY Ahn <yongyeol@gmail.com>
License: MIT
Classifier: Programming Language :: Python :: 3
Classifier: Programming Language :: Python :: 3.12
Classifier: License :: OSI Approved :: MIT License
Classifier: Operating System :: OS Independent
Requires-Dist: lxml>=6.0.2
Requires-Dist: matplotlib>=3.10.7
Requires-Dist: pillow>=12.0.0
Requires-Dist: pydantic>=2.12.5
Requires-Dist: pymupdf>=1.26.6
Requires-Dist: pyyaml>=6.0.3
Requires-Dist: seaborn>=0.13.2
Requires-Dist: watchfiles>=1.0.0
Requires-Python: >=3.12
Project-URL: Homepage, https://github.com/yy/figquilt
Project-URL: Repository, https://github.com/yy/figquilt
